Morfessor_FlatCat-1.0.8.data/scripts/flatcat
Morfessor_FlatCat-1.0.8.data/scripts/flatcat-advanced-segment.py
Morfessor_FlatCat-1.0.8.data/scripts/flatcat-evaluate
Morfessor_FlatCat-1.0.8.data/scripts/flatcat-restitch.py
Morfessor_FlatCat-1.0.8.data/scripts/flatcat-segment
Morfessor_FlatCat-1.0.8.data/scripts/flatcat-train
Morfessor_FlatCat-1.0.8.dist-info/DESCRIPTION.rst
Morfessor_FlatCat-1.0.8.dist-info/METADATA
Morfessor_FlatCat-1.0.8.dist-info/RECORD
Morfessor_FlatCat-1.0.8.dist-info/WHEEL
Morfessor_FlatCat-1.0.8.dist-info/metadata.json
Morfessor_FlatCat-1.0.8.dist-info/top_level.txt
flatcat/__init__.py
flatcat/categorizationscheme.py
flatcat/cmd.py
flatcat/diagnostics.py
flatcat/exception.py
flatcat/flatcat.py
flatcat/io.py
flatcat/reduced.py
flatcat/utils.py
flatcat/tests/__init__.py
flatcat/tests/flatcat_test.py
