Metadata-Version: 2.0
Name: Morfessor-FlatCat
Version: 1.0.8
Summary: Morfessor FlatCat
Home-page: https://github.com/aalto-speech/flatcat
Author: Stig-Arne Gronroos
Author-email: morfessor@cis.hut.fi
License: BSD
Keywords: semi-supervised morphological segmentation
Platform: UNKNOWN
Classifier: Development Status :: 4 - Beta
Classifier: Intended Audience :: Science/Research
Classifier: License :: OSI Approved :: BSD License
Classifier: Operating System :: OS Independent
Classifier: Programming Language :: Python :: 2.7
Classifier: Programming Language :: Python :: 3
Classifier: Topic :: Scientific/Engineering
Requires-Dist: morfessor (>=2.0.2alpha1)
Provides-Extra: docs
Requires-Dist: sphinx; extra == 'docs'
Requires-Dist: sphinxcontrib-napoleon; extra == 'docs'
